Wav2Lip/__init__.py
Wav2Lip/audio.py
Wav2Lip/color_syncnet_train.py
Wav2Lip/hparams.py
Wav2Lip/hq_wav2lip_train.py
Wav2Lip/inference.py
Wav2Lip/preprocess.py
Wav2Lip/wav2lip_train.py
Wav2Lip/wrapper_app.py
Wav2Lip/face_detection/__init__.py
Wav2Lip/face_detection/api.py
Wav2Lip/face_detection/models.py
Wav2Lip/face_detection/utils.py
Wav2Lip/face_detection/detection/__init__.py
Wav2Lip/face_detection/detection/core.py
Wav2Lip/face_detection/detection/sfd/__init__.py
Wav2Lip/face_detection/detection/sfd/bbox.py
Wav2Lip/face_detection/detection/sfd/detect.py
Wav2Lip/face_detection/detection/sfd/net_s3fd.py
Wav2Lip/face_detection/detection/sfd/sfd_detector.py
Wav2Lip/models/__init__.py
Wav2Lip/models/conv.py
Wav2Lip/models/syncnet.py
Wav2Lip/models/wav2lip.py
Wav2Lipy-0.0.1.dist-info/METADATA
Wav2Lipy-0.0.1.dist-info/WHEEL
Wav2Lipy-0.0.1.dist-info/top_level.txt
Wav2Lipy-0.0.1.dist-info/RECORD
