Metadata-Version: 2.1
Name: Wav2Lipy
Version: 0.0.1
Summary: Wrapper Package for LipGan Project
Home-page: UNKNOWN
Author: Mehdi Hosseini Moghadam, Hanie Poursina
Author-email: <m.h.moghadam1996@gmail.com> , <hanieh.poursina@gmail.com>
License: UNKNOWN
Keywords: python,GAN,LipGan,Speech,Lip-syncing,Video Lip-syncing,Image Lip-syncing,Audio Lip-syncingSpeech to gesture
Platform: UNKNOWN
Classifier: Development Status :: 1 - Planning
Classifier: Intended Audience :: Developers
Classifier: Programming Language :: Python :: 3
Classifier: Operating System :: Unix
Classifier: Operating System :: MacOS :: MacOS X
Classifier: Operating System :: Microsoft :: Windows
Requires-Dist: librosa (==0.7.0)
Requires-Dist: numpy (==1.17.1)
Requires-Dist: opencv-contrib-python (>=4.2.0.34)
Requires-Dist: opencv-python (==4.1.0.25)
Requires-Dist: torch (==1.1.0)
Requires-Dist: torchvision (==0.3.0)
Requires-Dist: tqdm (==4.45.0)
Requires-Dist: numba (==0.48)
